ellipsisAI/__init__.py
ellipsisAI-0.1.3.dist-info/LICENSE
ellipsisAI-0.1.3.dist-info/METADATA
ellipsisAI-0.1.3.dist-info/WHEEL
ellipsisAI-0.1.3.dist-info/top_level.txt
ellipsisAI-0.1.3.dist-info/RECORD
