Metadata-Version: 2.1
Name: ellipsisAI
Version: 0.1.3
Summary: Package to use Ellipsis Drive for AI
Home-page: https://github.com/ellipsis-drive-internal/python-package-AI
Author: Daniel van der Maas
Author-email: daniel@ellipsis-drive.com
Classifier: Programming Language :: Python :: 3
Classifier: License :: OSI Approved :: MIT License
Classifier: Operating System :: OS Independent
Requires-Python: >=3.6
License-File: LICENSE
Requires-Dist: ellipsis
Requires-Dist: numpy
Requires-Dist: tifffile
Requires-Dist: Pillow
Requires-Dist: requests
Requires-Dist: rasterio
Requires-Dist: geopandas
Requires-Dist: shapely
Requires-Dist: pandas
